package_name/__init__.py
pywebcon-2.0.0.dist-info/LICENSE
pywebcon-2.0.0.dist-info/METADATA
pywebcon-2.0.0.dist-info/WHEEL
pywebcon-2.0.0.dist-info/top_level.txt
pywebcon-2.0.0.dist-info/RECORD
