Metadata-Version: 2.1
Name: pywebcon
Version: 2.0.0
Summary: Check if websites/apis are online
Home-page: UNKNOWN
Author: pydob
License: UNKNOWN
Platform: UNKNOWN
Classifier: Programming Language :: Python :: 3
Classifier: License :: OSI Approved :: MIT License
Classifier: Operating System :: OS Independent
Requires-Python: >=3.6
